{
  "presetId": "wooden_plane_empty",
  "displayName": "preset.dscombat.wooden_plane_empty",
  "aircraft_type": 0,
  "item": "dscombat:wooden_plane",
  "health": 40.0,
  "max_health": 40.0,
  "mass": 8.0,
  "max_speed": 0.9,
  "stealth": 1.0,
  "idleheat": 1.0,
  "turn_radius": 16.0,
  "maxroll": 5.0,
  "maxpitch": 3.0,
  "maxyaw": 2.0,
  "rolltorque": 1.5,
  "pitchtorque": 2.5,
  "yawtorque": 4.5,
  "throttledown": 0.06,
  "throttleup": 0.02,
  "wing_area": 6.0,
  "textures": {
    "12": "dscombat:textures/entities/wooden_plane/brown.png"
  },
  "dyecolor": 12,
  "ingredients": [
    {
      "item": "minecraft:oak_planks",
      "num": 60
    },
    {
      "item": "dscombat:cockpit",
      "num": 1
    },
    {
      "item": "dscombat:propeller",
      "num": 1
    }
  ],
  "slots": [
    {
      "name": "slotname.dscombat.pilot_seat",
      "slot_type": 0,
      "slot_posx": 0.0,
      "slot_posy": -0.4,
      "slot_posz": 0.0,
      "uix": 48,
      "uiy": 20,
      "zRot": 0.0,
      "data": {
        "itemid": "dscombat:seat"
      }
    },
    {
      "name": "slotname.dscombat.left_wing_1",
      "slot_type": 1,
      "slot_posx": 1.5,
      "slot_posy": 0.0,
      "slot_posz": 0.0,
      "uix": 48,
      "uiy": 40,
      "zRot": 0.0
    },
    {
      "name": "slotname.dscombat.right_wing_1",
      "slot_type": 1,
      "slot_posx": -1.5,
      "slot_posy": 0.0,
      "slot_posz": 0.0,
      "uix": 48,
      "uiy": 60,
      "zRot": 0.0
    },
    {
      "name": "slotname.dscombat.internal_1",
      "slot_type": 10,
      "slot_posx": 0.0,
      "slot_posy": 0.0,
      "slot_posz": 0.0,
      "uix": 48,
      "uiy": 100,
      "zRot": 0.0
    },
    {
      "name": "slotname.dscombat.internal_2",
      "slot_type": 3,
      "slot_posx": 0.0,
      "slot_posy": 0.0,
      "slot_posz": 0.0,
      "uix": 68,
      "uiy": 100,
      "zRot": 0.0
    },
    {
      "name": "slotname.dscombat.internal_3",
      "slot_type": 3,
      "slot_posx": 0.0,
      "slot_posy": 0.0,
      "slot_posz": 0.0,
      "uix": 88,
      "uiy": 100,
      "zRot": 0.0
    }
  ],
  "landing_gear": true,
  "is_craftable": false
}